MLFairnessPipeline/.DS_Store
MLFairnessPipeline/Inprocessing.py
MLFairnessPipeline/Postprocessing.py
MLFairnessPipeline/Preprocessing.py
MLFairnessPipeline/Utilities.py
MLFairnessPipeline/__init__.py
MLFairnessPipeline-0.22.dist-info/LICENSE
MLFairnessPipeline-0.22.dist-info/METADATA
MLFairnessPipeline-0.22.dist-info/WHEEL
MLFairnessPipeline-0.22.dist-info/top_level.txt
MLFairnessPipeline-0.22.dist-info/RECORD
