Metadata-Version: 2.1
Name: MLFairnessPipeline
Version: 0.22
Summary: An end to end ML Fairness Pipeline
Home-page: https://github.com/markbentivegna/MLFairnessPipeline
Author: Mark Bentivegna
Author-email: markbentivegna@gmail.com
License: UNKNOWN
Platform: UNKNOWN
Classifier: Programming Language :: Python :: 3
Classifier: License :: OSI Approved :: MIT License
Classifier: Operating System :: OS Independent
